highflame/__init__.py
highflame/chat_completions.py
highflame/client.py
highflame/exceptions.py
highflame/model_adapters.py
highflame/models.py
highflame/py.typed
highflame/services/aispm_service.py
highflame/services/gateway_service.py
highflame/services/guardrails_service.py
highflame/services/modelspec_service.py
highflame/services/provider_service.py
highflame/services/route_service.py
highflame/services/secret_service.py
highflame/services/template_service.py
highflame/services/trace_service.py
highflame/tracing_setup.py
highflame_cli/__init__.py
highflame_cli/__main__.py
highflame_cli/_internal/__init__.py
highflame_cli/_internal/commands.py
highflame_cli/cli.py
highflame-0.2.41.dist-info/METADATA
highflame-0.2.41.dist-info/WHEEL
highflame-0.2.41.dist-info/entry_points.txt
highflame-0.2.41.dist-info/licenses/LICENSE
highflame-0.2.41.dist-info/RECORD
